blsct/__init__.py
blsct/_blsct.cpython-312-x86_64-linux-gnu.so
blsct/address.py
blsct/address_encoding.py
blsct/amount_recovery_req.py
blsct/amount_recovery_res.py
blsct/blsct.i
blsct/blsct.py
blsct/chain.py
blsct/clonable.py
blsct/ctx.py
blsct/ctx_id.py
blsct/ctx_in.py
blsct/ctx_ins.py
blsct/ctx_out.py
blsct/ctx_outs.py
blsct/hash_id.py
blsct/managed_obj.py
blsct/out_point.py
blsct/point.py
blsct/pretty_printable.py
blsct/range_proof.py
blsct/scalar.py
blsct/script.py
blsct/serializable.py
blsct/signature.py
blsct/sub_addr.py
blsct/sub_addr_id.py
blsct/token_id.py
blsct/tx_in.py
blsct/tx_out.py
blsct/view_tag.py
blsct/keys/__init__.py
blsct/keys/child_key.py
blsct/keys/double_public_key.py
blsct/keys/priv_spending_key.py
blsct/keys/public_key.py
blsct/keys/tx_key.py
navio_blsct-0.0.37.dist-info/METADATA
navio_blsct-0.0.37.dist-info/WHEEL
navio_blsct-0.0.37.dist-info/top_level.txt
navio_blsct-0.0.37.dist-info/RECORD
navio_blsct-0.0.37.dist-info/licenses/LICENSE
