Metadata-Version: 2.4
Name: navio_blsct
Version: 0.0.37
Summary: Python binding for the Navio blsct library
Project-URL: Homepage, https://github.com/nav-io/libblsct-bindings
Project-URL: Repository, https://github.com/nav-io/libblsct-bindings
Requires-Python: >=3.12
License-File: LICENSE
Dynamic: license-file
